multiolib/__init__.py
multiolib/bin/cache-generator-fesom-2-mir
multiolib/bin/fesom-cache-generator
multiolib/bin/fesom-cache-validator
multiolib/bin/fesom-spmvm-validator
multiolib/bin/multio-convert-trace-log
multiolib/bin/multio-encode-ocean
multiolib/bin/multio-feed
multiolib/bin/multio-generate-grib-template
multiolib/bin/multio-generate-healpix-cache
multiolib/bin/multio-hammer
multiolib/bin/multio-probe
multiolib/bin/multio-replay-nemo-capi
multiolib/bin/multio-replay-nemo-capi-partial-agg
multiolib/bin/multio-replay-nemo-fapi
multiolib/include/multio/LibMultio.h
multiolib/include/multio/multio_config.h
multiolib/include/multio/multio_ecbuild_config.h
multiolib/include/multio/multio_version.h
multiolib/include/multio/action/Action.h
multiolib/include/multio/action/ActionStatistics.h
multiolib/include/multio/action/ChainedAction.h
multiolib/include/multio/action/Plan.h
multiolib/include/multio/config/ComponentConfiguration.h
multiolib/include/multio/config/MetadataMappings.h
multiolib/include/multio/config/MultioConfiguration.h
multiolib/include/multio/config/PathConfiguration.h
multiolib/include/multio/config/PlanConfiguration.h
multiolib/include/multio/domain/Domain.h
multiolib/include/multio/domain/Mappings.h
multiolib/include/multio/domain/Mask.h
multiolib/include/multio/domain/MaskCompression.h
multiolib/include/multio/ifsio/EncodeBitsPerValue.h
multiolib/include/multio/ifsio/ifsio.h
multiolib/include/multio/message/BaseMetadata.h
multiolib/include/multio/message/Glossary.h
multiolib/include/multio/message/Message.h
multiolib/include/multio/message/Metadata.h
multiolib/include/multio/message/MetadataException.h
multiolib/include/multio/message/MetadataMapping.h
multiolib/include/multio/message/MetadataMatcher.h
multiolib/include/multio/message/MetadataTypes.h
multiolib/include/multio/message/MetadataValue.h
multiolib/include/multio/message/Parametrization.h
multiolib/include/multio/message/Peer.h
multiolib/include/multio/message/PrehashedKey.h
multiolib-2.5.3.dist-info/licenses/AUTHORS
multiolib-2.5.3.dist-info/licenses/LICENSE
multiolib-2.5.3.dist-info/METADATA
multiolib-2.5.3.dist-info/WHEEL
multiolib-2.5.3.dist-info/top_level.txt
multiolib-2.5.3.dist-info/RECORD
