Metadata-Version: 2.4
Name: multiolib
Version: 2.5.3
Summary: "multiolib"
Author: file: AUTHORS
License-File: LICENSE
License-File: AUTHORS
Requires-Dist: eckitlib<2,>=1.29.2
Requires-Dist: eccodeslib<3,>=2.42.0
Requires-Dist: metkitlib<2,>=1.14.0
Requires-Dist: atlaslib-ecmwf<1,>=0.43.0
Requires-Dist: fdb5lib<6,>=5.15.12.dev0
Requires-Dist: mirlib<2,>=1.25.1
Requires-Dist: fckitlib<1,>=0.14.0
Dynamic: license-file
Dynamic: requires-dist
